onlyoffice.plone-4.0.0-py3.10-nspkg.pth
onlyoffice/plone/__init__.py
onlyoffice/plone/configure.zcml
onlyoffice/plone/interfaces.py
onlyoffice/plone/permissions.zcml
onlyoffice/plone/setuphandlers.py
onlyoffice/plone/testing.py
onlyoffice/plone/upgrades.py
onlyoffice/plone/upgrades.zcml
onlyoffice/plone/browser/__init__.py
onlyoffice/plone/browser/actions.py
onlyoffice/plone/browser/api.py
onlyoffice/plone/browser/configure.zcml
onlyoffice/plone/browser/controlpanel.py
onlyoffice/plone/browser/interfaces.py
onlyoffice/plone/browser/menu.py
onlyoffice/plone/browser/app_data/az-Latn-AZ/new.docx
onlyoffice/plone/browser/app_data/az-Latn-AZ/new.docxf
onlyoffice/plone/browser/app_data/az-Latn-AZ/new.pptx
onlyoffice/plone/browser/app_data/az-Latn-AZ/new.xlsx
onlyoffice/plone/browser/app_data/bg-BG/new.docx
onlyoffice/plone/browser/app_data/bg-BG/new.docxf
onlyoffice/plone/browser/app_data/bg-BG/new.pptx
onlyoffice/plone/browser/app_data/bg-BG/new.xlsx
onlyoffice/plone/browser/app_data/cs-CZ/new.docx
onlyoffice/plone/browser/app_data/cs-CZ/new.docxf
onlyoffice/plone/browser/app_data/cs-CZ/new.pptx
onlyoffice/plone/browser/app_data/cs-CZ/new.xlsx
onlyoffice/plone/browser/app_data/de-DE/new.docx
onlyoffice/plone/browser/app_data/de-DE/new.docxf
onlyoffice/plone/browser/app_data/de-DE/new.pptx
onlyoffice/plone/browser/app_data/de-DE/new.xlsx
onlyoffice/plone/browser/app_data/el-GR/new.docx
onlyoffice/plone/browser/app_data/el-GR/new.docxf
onlyoffice/plone/browser/app_data/el-GR/new.pptx
onlyoffice/plone/browser/app_data/el-GR/new.xlsx
onlyoffice/plone/browser/app_data/en-GB/new.docx
onlyoffice/plone/browser/app_data/en-GB/new.docxf
onlyoffice/plone/browser/app_data/en-GB/new.pptx
onlyoffice/plone/browser/app_data/en-GB/new.xlsx
onlyoffice/plone/browser/app_data/en-US/new.docx
onlyoffice/plone/browser/app_data/en-US/new.docxf
onlyoffice/plone/browser/app_data/en-US/new.pptx
onlyoffice/plone/browser/app_data/en-US/new.xlsx
onlyoffice/plone/browser/app_data/es-ES/new.docx
onlyoffice.plone-4.0.0.dist-info/AUTHORS.md
onlyoffice.plone-4.0.0.dist-info/LICENSE
onlyoffice.plone-4.0.0.dist-info/METADATA
onlyoffice.plone-4.0.0.dist-info/WHEEL
onlyoffice.plone-4.0.0.dist-info/entry_points.txt
onlyoffice.plone-4.0.0.dist-info/namespace_packages.txt
onlyoffice.plone-4.0.0.dist-info/top_level.txt
onlyoffice.plone-4.0.0.dist-info/RECORD
