Metadata-Version: 2.1
Name: onlyoffice.plone
Version: 4.0.0
Summary: Plone ONLYOFFICE integration plugin
Home-page: https://github.com/ONLYOFFICE/onlyoffice-plone
Author: Ascensio System SIA
Author-email: integration@onlyoffice.com
License: Apache-2.0 License
Project-URL: PyPI, https://pypi.python.org/pypi/onlyoffice.plone
Project-URL: Source, https://github.com/ONLYOFFICE/onlyoffice-plone
Project-URL: Tracker, https://github.com/ONLYOFFICE/onlyoffice-plone/issues
Keywords: Python Plone
Classifier: Environment :: Web Environment
Classifier: Framework :: Plone
Classifier: Framework :: Plone :: Addon
Classifier: Framework :: Plone :: 6.0
Classifier: Programming Language :: Python
Classifier: Programming Language :: Python :: 3.8
Classifier: Programming Language :: Python :: 3.9
Classifier: Programming Language :: Python :: 3.10
Classifier: Programming Language :: Python :: 3.11
Classifier: Operating System :: OS Independent
Classifier: License :: OSI Approved :: Apache Software License
License-File: LICENSE
License-File: AUTHORS.md
Requires-Dist: setuptools
Requires-Dist: z3c.jbot
Requires-Dist: plone.api
Requires-Dist: plone.restapi
Requires-Dist: plone.app.dexterity
Provides-Extra: test
Requires-Dist: plone.app.testing ; extra == 'test'
Requires-Dist: plone.testing ; extra == 'test'
Requires-Dist: plone.app.contenttypes ; extra == 'test'
Requires-Dist: plone.app.robotframework[debug] ; extra == 'test'
